README.md
setup.cfg
setup.py
distributions_antest/Binomialdistribution.py
distributions_antest/Gaussiandistribution.py
distributions_antest/Generaldistribution.py
distributions_antest/__init__.py
distributions_antest.egg-info/PKG-INFO
distributions_antest.egg-info/SOURCES.txt
distributions_antest.egg-info/dependency_links.txt
distributions_antest.egg-info/not-zip-safe
distributions_antest.egg-info/top_level.txt